actinia_statistic_plugin/__init__.py
actinia_statistic_plugin/endpoints.py
actinia_statistic_plugin/ephemeral_raster_area_stats.py
actinia_statistic_plugin/ephemeral_raster_area_stats_univar.py
actinia_statistic_plugin/ephemeral_strds_area_stats.py
actinia_statistic_plugin/ephemeral_strds_area_stats_univar.py
actinia_statistic_plugin/raster_sampling.py
actinia_statistic_plugin/response_models.py
actinia_statistic_plugin/strds_sampling.py
actinia_statistic_plugin/strds_sampling_geojson.py
actinia_statistic_plugin/vector_sampling.py
actinia_statistic_plugin-0.4.0.dist-info/licenses/AUTHORS.rst
actinia_statistic_plugin-0.4.0.dist-info/licenses/LICENSE.txt
actinia_statistic_plugin-0.4.0.dist-info/METADATA
actinia_statistic_plugin-0.4.0.dist-info/WHEEL
actinia_statistic_plugin-0.4.0.dist-info/top_level.txt
actinia_statistic_plugin-0.4.0.dist-info/RECORD
