Metadata-Version: 2.4
Name: actinia-statistic-plugin
Version: 0.4.0
Summary: Actinia plugin for efficient statistic computing
Author: Markus Neteler, Carmen Tawalika, Anika Weinmann, Lina Krisztian, Soeren Gebbert, Marc Jansen, Julia Haas
Project-URL: Homepage, https://github.com/mundialis/actinia-statistic-plugin
Project-URL: Tutorial, https://mundialis.github.io/actinia_core
Project-URL: API_Docs, https://redocly.github.io/redoc/?url=https://actinia.mundialis.de/latest/swagger.json
Keywords: processing,earth observation,cloud-based processing,rest api,gis,grass gis,osgeo,stac
Classifier: License :: OSI Approved :: MIT License
Classifier: Programming Language :: Python :: 3
Requires-Python: >=3.8
License-File: LICENSE.txt
License-File: AUTHORS.rst
Provides-Extra: test
Requires-Dist: pytest; extra == "test"
Dynamic: license-file
